scrapse/__init__.py
scrapse/__main__.py
scrapse/judgment/anonimization_utils.py
scrapse/judgment/commands/extraction.py
scrapse/judgment/conversion_utils.py
scrapse/judgment/extraction_utils.py
scrapse/judgment/general_utils.py
scrapse/judgment/judgment.py
scrapse/leggitalia/commands/dump_judgments.py
scrapse/leggitalia/commands/save_cookie.py
scrapse/leggitalia/commands/scrap_judgments.py
scrapse/leggitalia/commands/scrap_voices.py
scrapse/leggitalia/commands/show_filters.py
scrapse/leggitalia/comuni.txt
scrapse/leggitalia/leggitalia.py
scrapse/leggitalia/utils.py
scrapse/main.py
scrapse-0.3.9.dist-info/METADATA
scrapse-0.3.9.dist-info/WHEEL
scrapse-0.3.9.dist-info/entry_points.txt
scrapse-0.3.9.dist-info/RECORD
