Metadata-Version: 2.1
Name: scrapse
Version: 0.3.9
Summary: Package to download and manage judgments
Home-page: https://gitlab.di.unito.it/ngupp/ngupp-scrapse
Keywords: scraping,judgments
Author: zaharia laurentiu jr marius
Author-email: zaharialorenzo@gmail.com
Maintainer: zaharia laurentiu jr marius
Maintainer-email: zaharialorenzo@gmail.com
Requires-Python: >=3.8,<4.0
Classifier: Programming Language :: Python :: 3
Classifier: Programming Language :: Python :: 3.8
Classifier: Programming Language :: Python :: 3.9
Classifier: Programming Language :: Python :: 3.10
Classifier: Programming Language :: Python :: 3.11
Requires-Dist: beautifulsoup4 (>=4.11.2,<5.0.0)
Requires-Dist: docx (>=0.2.4,<0.3.0)
Requires-Dist: docx2txt (>=0.8,<0.9)
Requires-Dist: pandas (>=2.0.0,<3.0.0)
Requires-Dist: requests (>=2.28.2,<3.0.0)
Requires-Dist: spacy (>=3.5.1,<4.0.0)
Requires-Dist: typer[all] (>=0.7.0,<0.8.0)
Project-URL: Repository, https://gitlab.di.unito.it/ngupp/ngupp-scrapse
